ko_pack/Aqouthe_.py
ko_pack/Aqouthe_module.py
ko_pack/__init__.py
Bogidden-2.1.3.5.dist-info/LICENCE
Bogidden-2.1.3.5.dist-info/METADATA
Bogidden-2.1.3.5.dist-info/WHEEL
Bogidden-2.1.3.5.dist-info/top_level.txt
Bogidden-2.1.3.5.dist-info/RECORD
