Metadata-Version: 2.1
Name: Bogidden
Version: 2.1.3.5
Summary: A module containing only basic functions
Home-page: UNKNOWN
Author: Aqouthe
Author-email: hoonie0929@gmail.com
License: MIT
Platform: UNKNOWN
Requires-Python: >=3
License-File: LICENCE
